wouaka/__init__.py
wouaka/client.py
wouaka/exceptions.py
wouaka/webhooks.py
wouaka/modules/__init__.py
wouaka/modules/iea.py
wouaka/modules/kyc.py
wouaka/modules/trustlink.py
wouaka-1.0.0.dist-info/licenses/LICENSE
wouaka-1.0.0.dist-info/METADATA
wouaka-1.0.0.dist-info/WHEEL
wouaka-1.0.0.dist-info/top_level.txt
wouaka-1.0.0.dist-info/RECORD
