Metadata-Version: 2.4
Name: wouaka
Version: 1.0.0
Summary: SDK Python officiel pour l'API Wouaka - Scoring crédit et KYC pour l'Afrique de l'Ouest
Home-page: https://github.com/wouaka/wouaka-python-sdk
Author: Wouaka SAS
Author-email: Wouaka SAS <support@wouaka.com>
License: MIT
Project-URL: Homepage, https://wouaka.com/developers/sdks
Project-URL: Documentation, https://docs.wouaka.com
Project-URL: Repository, https://github.com/wouaka/wouaka-python-sdk
Project-URL: Issues, https://github.com/wouaka/wouaka-python-sdk/issues
Keywords: wouaka,credit-scoring,kyc,verification,africa,uemoa,fintech,microfinance
Classifier: Development Status :: 5 - Production/Stable
Classifier: Intended Audience :: Developers
Classifier: Intended Audience :: Financial and Insurance Industry
Classifier: Topic :: Office/Business :: Financial
Classifier: License :: OSI Approved :: MIT License
Classifier: Programming Language :: Python :: 3
Classifier: Programming Language :: Python :: 3.8
Classifier: Programming Language :: Python :: 3.9
Classifier: Programming Language :: Python :: 3.10
Classifier: Programming Language :: Python :: 3.11
Classifier: Programming Language :: Python :: 3.12
Requires-Python: >=3.8
License-File: LICENSE
Requires-Dist: requests>=2.28.0
Requires-Dist: python-dateutil>=2.8.2
Requires-Dist: pydantic>=2.0.0
Requires-Dist: cryptography>=41.0.0
Provides-Extra: dev
Requires-Dist: pytest>=7.0.0; extra == "dev"
Requires-Dist: pytest-cov>=4.0.0; extra == "dev"
Requires-Dist: black>=23.0.0; extra == "dev"
Requires-Dist: flake8>=6.0.0; extra == "dev"
Requires-Dist: mypy>=1.0.0; extra == "dev"
Provides-Extra: docs
Requires-Dist: sphinx>=6.0.0; extra == "docs"
Requires-Dist: sphinx-rtd-theme>=1.2.0; extra == "docs"
Dynamic: author
Dynamic: home-page
Dynamic: license-file
Dynamic: requires-python
